{
    "product_id": "granite-tetocserep",
    "name": "Granite Classic tetőcserépA GRANITE betoncserepek sík felületükkel a manapság népszerű, letisztult formavilág építőelemi közé tartoznak.  Ez a tetőcserép modell azonban nem csu...Megnézem",
    "description": "",
    "url": "https://www.leier.hu/hu/termekek/granite-tetocserep",
    "category_url": "https://www.leier.hu/hu/termekeink/betoncserepek",
    "price_info": "",
    "specifications": {},
    "documents": {
        "doc_0": {
            "title": "Akciós termékkínálat",
            "url": "https://www.leier.hu/uploads/files/Leier_tavaszi_ajanlat_2025-web-67d7c49cbc0af.pdf",
            "type": "pdf"
        },
        "doc_1": {
            "title": "Granite tetőcserép termékadatlap (pdf)",
            "url": "https://www.leier.hu/uploads/files/Leier-Granite-tetocserep-termekadatlap-673afea9020e7.pdf",
            "type": "pdf"
        },
        "doc_2": {
            "title": "Új Toscana szellőzőcserép termékbemutató kiadvány (pdf)",
            "url": "https://www.leier.hu/uploads/files/Toscana-szellözöcserep-szorolap.pdf",
            "type": "pdf"
        },
        "doc_3": {
            "title": "Betoncserepek - Hajdúszoboszló - Teljesítménynyilatkozat LE HA490-04 (pdf)",
            "url": "https://www.leier.hu/uploads/files/Beton-tetocserep-Hajduszoboszlo-65f14857ae292.pdf",
            "type": "pdf"
        },
        "doc_4": {
            "title": "Leier tavaszi termékkínálat 2025 (pdf)",
            "url": "https://www.leier.hu/uploads/files/Leier_tavaszi_ajanlat_2025-web-67d7c49cb7579.pdf",
            "type": "pdf"
        },
        "doc_5": {
            "title": "Leier betoncserép prospektus (pdf)",
            "url": "https://www.leier.hu/uploads/files/Leier_betoncserep_prospektus_2025_OK-web-67d946549aaa6.pdf",
            "type": "pdf"
        },
        "doc_6": {
            "title": "Tetőfedő rendszerek alkalmazástechnika és tervezési segédlet (pdf)",
            "url": "https://www.leier.hu/uploads/files/2025_A4_-_Tetőfedés_-_WEB-67e699f36cfcc.pdf",
            "type": "pdf"
        },
        "doc_7": {
            "title": "Tetőfedés árlista viszonteladók részére 2025 (pdf)",
            "url": "https://www.leier.hu/uploads/files/Arlista-tetofedes-2025-685aa5ac29ecd.pdf",
            "type": "pdf"
        },
        "doc_8": {
            "title": "Akciós termékkínálat",
            "url": "https://www.leier.hu/uploads/files/Leier_tavaszi_ajanlat_2025-web-67d7c49cbc0af.pdf",
            "type": "pdf"
        },
        "doc_9": {
            "title": "Granite tetőcserép termékadatlap (pdf)",
            "url": "https://www.leier.hu/uploads/files/Leier-Granite-tetocserep-termekadatlap-673afea9020e7.pdf",
            "type": "pdf"
        },
        "doc_10": {
            "title": "Új Toscana szellőzőcserép termékbemutató kiadvány (pdf)",
            "url": "https://www.leier.hu/uploads/files/Toscana-szellözöcserep-szorolap.pdf",
            "type": "pdf"
        },
        "doc_11": {
            "title": "Betoncserepek - Hajdúszoboszló - Teljesítménynyilatkozat LE HA490-04 (pdf)",
            "url": "https://www.leier.hu/uploads/files/Beton-tetocserep-Hajduszoboszlo-65f14857ae292.pdf",
            "type": "pdf"
        },
        "doc_12": {
            "title": "Leier tavaszi termékkínálat 2025 (pdf)",
            "url": "https://www.leier.hu/uploads/files/Leier_tavaszi_ajanlat_2025-web-67d7c49cb7579.pdf",
            "type": "pdf"
        },
        "doc_13": {
            "title": "Leier betoncserép prospektus (pdf)",
            "url": "https://www.leier.hu/uploads/files/Leier_betoncserep_prospektus_2025_OK-web-67d946549aaa6.pdf",
            "type": "pdf"
        },
        "doc_14": {
            "title": "Tetőfedő rendszerek alkalmazástechnika és tervezési segédlet (pdf)",
            "url": "https://www.leier.hu/uploads/files/2025_A4_-_Tetőfedés_-_WEB-67e699f36cfcc.pdf",
            "type": "pdf"
        },
        "doc_15": {
            "title": "Tetőfedés árlista viszonteladók részére 2025 (pdf)",
            "url": "https://www.leier.hu/uploads/files/Arlista-tetofedes-2025-685aa5ac29ecd.pdf",
            "type": "pdf"
        },
        "doc_16": {
            "title": "Akciós termékkínálat",
            "url": "https://www.leier.hu/uploads/files/Leier_tavaszi_ajanlat_2025-web-67d7c49cbc0af.pdf",
            "type": "pdf"
        },
        "doc_17": {
            "title": "Granite-carbon1-65e87c336ea61",
            "url": "https://www.leier.hu/uploads/files/Granite-carbon1-65e87c336ea61.png",
            "type": "document"
        },
        "doc_18": {
            "title": "Granite_teglavoros-661f869991ec1",
            "url": "https://www.leier.hu/uploads/files/Granite_teglavoros-661f869991ec1.PNG",
            "type": "document"
        },
        "doc_19": {
            "title": "granite-fekete-646f642d1dc42",
            "url": "https://www.leier.hu/uploads/files/granite-fekete-646f642d1dc42.png",
            "type": "document"
        },
        "doc_20": {
            "title": "sotetbarna",
            "url": "https://www.leier.hu/uploads/files/sotetbarna.png",
            "type": "document"
        },
        "doc_21": {
            "title": "Granite Classic betoncserép",
            "url": "https://photos.leier.eu/pV59_Ha-yhwX5C73vbF4nULmHuk=/filters:watermark(https://www.leier.hu/uploads/files/Leier-betoncserep-logo-fekvo-szlogennel-1.jpg,-20,20,0,20)/https%3A%2F%2Fwww.leier.hu%2Fuploads%2Ffiles%2FGranite_Classic_carbon-Balatonszlos__7_.jpg",
            "type": "document"
        },
        "doc_22": {
            "title": "Granite Classic carbon betoncserép",
            "url": "https://photos.leier.eu/Y6RVdyu7uOUStIIm0o6-YHmpF1g=/filters:watermark(https://www.leier.hu/uploads/files/Leier-betoncserep-logo-fekvo-szlogennel-1.jpg,-20,20,0,20)/https%3A%2F%2Fwww.leier.hu%2Fuploads%2Ffiles%2FGranite_Classic_fekete-Balatonszlos__7_.jpg",
            "type": "document"
        },
        "doc_23": {
            "title": "Granite Classic carbon betoncserép",
            "url": "https://photos.leier.eu/Wy8dIiuHE_nW3_KaltOVVTEJoNc=/filters:watermark(https://www.leier.hu/uploads/files/Leier-betoncserep-logo-fekvo-szlogennel-1.jpg,-20,20,0,20)/https%3A%2F%2Fwww.leier.hu%2Fuploads%2Ffiles%2FGranite_Classic_fekete-Balatonszlos__3_.jpg",
            "type": "document"
        },
        "doc_24": {
            "title": "Granite Classic carbon betoncserép",
            "url": "https://photos.leier.eu/K1Sot99QGECD5l1JKmUHN6Kpj0I=/filters:watermark(https://www.leier.hu/uploads/files/Leier-betoncserep-logo-fekvo-szlogennel-1.jpg,-20,20,0,20)/https%3A%2F%2Fwww.leier.hu%2Fuploads%2Ffiles%2FGranite_Classic_fekete-Balatonszlos__14_.jpg",
            "type": "document"
        },
        "doc_25": {
            "title": "Granite Classic carbon betoncserép",
            "url": "https://photos.leier.eu/Z1q-mmgPWX6NsIn02Vj1xzS985s=/filters:watermark(https://www.leier.hu/uploads/files/Leier-betoncserep-logo-fekvo-szlogennel-1.jpg,-20,20,0,20)/https%3A%2F%2Fwww.leier.hu%2Fuploads%2Ffiles%2FGranite_Classic_carbon-Balatonszlos__1_.jpg",
            "type": "document"
        },
        "doc_26": {
            "title": "Granite Classic fekete betoncserép",
            "url": "https://photos.leier.eu/pUpiujiKd9dciHPSxIrW68n4SQQ=/filters:watermark(https://www.leier.hu/uploads/files/Leier-betoncserep-logo-fekvo-szlogennel-1.jpg,-20,20,0,20)/https%3A%2F%2Fwww.leier.hu%2Fuploads%2Ffiles%2FGranite-fekete-csere%25CC%2581p_nagyszentja%25CC%2581nos-1__18_.jpg",
            "type": "document"
        },
        "doc_27": {
            "title": "Granite Classic fekete betoncserép",
            "url": "https://photos.leier.eu/KiqlKS3OQ8k0q8atHWQuMYUteCU=/filters:watermark(https://www.leier.hu/uploads/files/Leier-betoncserep-logo-fekvo-szlogennel-1.jpg,-20,20,0,20)/https%3A%2F%2Fwww.leier.hu%2Fuploads%2Ffiles%2FGranite-fekete-csere%25CC%2581p_nagyszentja%25CC%2581nos-1__11_.jpg",
            "type": "document"
        },
        "doc_28": {
            "title": "Granite Classic fekete betoncserép",
            "url": "https://photos.leier.eu/l5fAgN_yLpfxm72hwR3pTSZZw70=/filters:watermark(https://www.leier.hu/uploads/files/Leier-betoncserep-logo-fekvo-szlogennel-1.jpg,-20,20,0,20)/https%3A%2F%2Fwww.leier.hu%2Fuploads%2Ffiles%2FLeier-Granite-tetocserep__1_.jpg",
            "type": "document"
        },
        "doc_29": {
            "title": "Granite Classic fekete betoncserép",
            "url": "https://photos.leier.eu/e3DOnYAwdzNXM70cdFqMmFMTj_I=/filters:watermark(https://www.leier.hu/uploads/files/Leier-betoncserep-logo-fekvo-szlogennel-1.jpg,-20,20,0,20)/https%3A%2F%2Fwww.leier.hu%2Fuploads%2Ffiles%2FLeier-Granite-tetocserep__2_.jpg",
            "type": "document"
        },
        "doc_30": {
            "title": "Granite tetőcserép termékadatlap (pdf)",
            "url": "https://www.leier.hu/uploads/files/Leier-Granite-tetocserep-termekadatlap-673afea9020e7.pdf",
            "type": "pdf"
        },
        "doc_31": {
            "title": "Új Toscana szellőzőcserép termékbemutató kiadvány (pdf)",
            "url": "https://www.leier.hu/uploads/files/Toscana-szellözöcserep-szorolap.pdf",
            "type": "pdf"
        },
        "doc_32": {
            "title": "Betoncserepek - Hajdúszoboszló - Teljesítménynyilatkozat LE HA490-04 (pdf)",
            "url": "https://www.leier.hu/uploads/files/Beton-tetocserep-Hajduszoboszlo-65f14857ae292.pdf",
            "type": "pdf"
        },
        "doc_33": {
            "title": "Leier tavaszi termékkínálat 2025 (pdf)",
            "url": "https://www.leier.hu/uploads/files/Leier_tavaszi_ajanlat_2025-web-67d7c49cb7579.pdf",
            "type": "pdf"
        },
        "doc_34": {
            "title": "Leier betoncserép prospektus (pdf)",
            "url": "https://www.leier.hu/uploads/files/Leier_betoncserep_prospektus_2025_OK-web-67d946549aaa6.pdf",
            "type": "pdf"
        },
        "doc_35": {
            "title": "Tetőfedő rendszerek alkalmazástechnika és tervezési segédlet (pdf)",
            "url": "https://www.leier.hu/uploads/files/2025_A4_-_Tetőfedés_-_WEB-67e699f36cfcc.pdf",
            "type": "pdf"
        },
        "doc_36": {
            "title": "Tetőfedés árlista viszonteladók részére 2025 (pdf)",
            "url": "https://www.leier.hu/uploads/files/Arlista-tetofedes-2025-685aa5ac29ecd.pdf",
            "type": "pdf"
        },
        "doc_37": {
            "title": "Letölthető dokumentumok",
            "url": "https://www.leier.hu/dokumentumtar#1859",
            "type": "document"
        },
        "doc_38": {
            "title": "Letölthető dokumentumok",
            "url": "https://www.leier.hu/dokumentumtar#1859",
            "type": "document"
        },
        "doc_39": {
            "title": "Prospektusok",
            "url": "https://www.leier.hu/dokumentumtar#1860",
            "type": "document"
        },
        "doc_40": {
            "title": "Letölthető dokumentumok",
            "url": "https://www.leier.hu/dokumentumtar#1859",
            "type": "document"
        },
        "doc_41": {
            "title": "Árlisták",
            "url": "https://www.leier.hu/dokumentumtar#1861",
            "type": "document"
        }
    },
    "document_count": 42,
    "images": [
        {
            "url": "https://photos.leier.eu/Vc48XPLbIJBNOoQW4H6aYoVI2lI=/647x327/https%3A%2F%2Fwww.leier.hu%2Fassets%2Ffront%2Fimages%2Fproduct-map.png",
            "alt": "Leier"
        },
        {
            "url": "https://photos.leier.eu/Vc48XPLbIJBNOoQW4H6aYoVI2lI=/647x327/https%3A%2F%2Fwww.leier.hu%2Fassets%2Ffront%2Fimages%2Fproduct-map.png",
            "alt": "Leier"
        },
        {
            "url": "https://www.leier.hu/assets/front/images/leier_main_logo.png",
            "alt": "Leier"
        },
        {
            "url": "https://photos.leier.eu/Kvp9N5fP-73QOB-xBruhzrU1wY4=/125x0/https%3A%2F%2Fwww.leier.hu%2Fuploads%2Ffiles%2FLeier-betoncserep-logo-fekvo-szlogennel-1.jpg",
            "alt": "Betoncserép"
        },
        {
            "url": "https://photos.leier.eu/O5T1K9BZhRpIT6RXADn8Fmt0wuM=/129x129/https%3A%2F%2Fwww.leier.hu%2Fuploads%2Ffiles%2FGranite-carbon1-65e87c336ea61.png",
            "alt": "Granite tetőcserép carbon"
        },
        {
            "url": "https://photos.leier.eu/mY06qfDjZqKTCLRw8v9PZ44nngs=/129x129/https%3A%2F%2Fwww.leier.hu%2Fuploads%2Ffiles%2FGranite_teglavoros-661f869991ec1.PNG",
            "alt": "Granite alapcserép téglavörös"
        },
        {
            "url": "https://photos.leier.eu/Riqqk8uEv-JgM4JbOrGqFKe00rA=/129x129/https%3A%2F%2Fwww.leier.hu%2Fuploads%2Ffiles%2Fgranite-fekete-646f642d1dc42.png",
            "alt": "Granite tetőcserép fekete"
        }
    ],
    "technical_data": {
        "Tetőhajlásszög": "30°-tól*",
        "Tetőlécméret": "minimum 30x50 mm*",
        "Méret": "33 x 42",
        "Tetőléctávolság": "maximum 34 cm*",
        "Tömeg": "5,3 kg/db",
        "Átfedés": "minimum 8,5 cm",
        "Névleges fedési szélesség": "304 +- 5 mm",
        "Szükséglet": "9,8 - 10,4 db/m2",
        "Típus": "Beton alapcserép*",
        "Elemszükséglet (kb.)": "10 db/m2",
        "kg/db": "5,3",
        "db/raklap": "210"
    },
    "features": [
        "Viszonteladóink",
        "Kalkulátorok",
        "Letölthető dokumentumok",
        "Rendszerház - akció"
    ]
}